<?xml version="1.0" encoding="utf-8" ?>
<dwsync>
<file name="llogwork.png.mno" server="10.100.16.201/sites/masonl/" local="130869745947940496" remote="130869766800000000" Dst="0" />
<file name="llogwork_r1_c2.png.mno" server="10.100.16.201/sites/masonl/" local="130869746529664496" remote="130869766800000000" Dst="0" />
<file name="llogwork_r1_c2_s2.png.mno" server="10.100.16.201/sites/masonl/" local="130869746548228496" remote="130869766800000000" Dst="0" />
<file name="llogwork_r1_c1.png.mno" server="10.100.16.201/sites/masonl/" local="130869746528416496" remote="130869766800000000" Dst="0" />
<file name="llogwork_r1_c1_s2.png.mno" server="10.100.16.201/sites/masonl/" local="130869746547136496" remote="130869766800000000" Dst="0" />
<file name="llogwork_r2_c2.png.mno" server="10.100.16.201/sites/masonl/" local="130869746540584496" remote="130869766800000000" Dst="0" />
<file name="llogwork_r2_c2_s2.png.mno" server="10.100.16.201/sites/masonl/" local="130869746559148496" remote="130869766800000000" Dst="0" />
<file name="llogwork_s2.png.mno" server="10.100.16.201/sites/masonl/" local="130869745949188496" remote="130869766800000000" Dst="0" />
<file name="llogwork_r1_c3.png.mno" server="10.100.16.201/sites/masonl/" local="130869746538556496" remote="130869766800000000" Dst="0" />
<file name="llogwork_r1_c3_s2.png.mno" server="10.100.16.201/sites/masonl/" local="130869746556964496" remote="130869766800000000" Dst="0" />
</dwsync>